LICENSE
README.md
setup.py
climetlab_demo_dataset/__init__.py
climetlab_demo_dataset.egg-info/PKG-INFO
climetlab_demo_dataset.egg-info/SOURCES.txt
climetlab_demo_dataset.egg-info/dependency_links.txt
climetlab_demo_dataset.egg-info/entry_points.txt
climetlab_demo_dataset.egg-info/requires.txt
climetlab_demo_dataset.egg-info/top_level.txt
climetlab_demo_dataset.egg-info/zip-safe